{
  "openapi": "3.0.0",
  "info": {
    "title": "Catalog Beer",
    "contact": {},
    "version": "1.0"
  },
  "servers": [
    {
      "url": "http://localhost:8081",
      "variables": {}
    }
  ],
  "paths": {
    "/beer": {
      "get": {
        "tags": [
            "Misc"
        ],
        "summary": "Catalog Beer",
        "operationId": "CatalogBeer",
        "parameters": [
          {
            "name": "food",
            "in": "query",
            "description": "",
            "required": true,
            "style": "form",
            "explode": true,
            "schema": {
              "type": "string",
              "example": "crusss"
            }
          }
        ],
        "responses": {
          "200": {
            "description": "",
            "headers": {}
          }
        },
        "deprecated": false
      }
    }
  },
  "tags": [
    {
      "name": "Misc",
      "description": ""
    }
  ]
}